featured/__init__.py
featured/admin.py
featured/models.py
featured/tests.py
featured/urls.py
featured/views.py
featured/locale/.gitkeep
featured/migrations/0001_initial.py
featured/migrations/__init__.py
featured/templatetags/__init__.py
featured/templatetags/featured_tags.py
django_featured_objects_redux-0.1.2.dist-info/LICENSE
django_featured_objects_redux-0.1.2.dist-info/METADATA
django_featured_objects_redux-0.1.2.dist-info/WHEEL
django_featured_objects_redux-0.1.2.dist-info/top_level.txt
django_featured_objects_redux-0.1.2.dist-info/RECORD
