Metadata-Version: 2.1
Name: django-featured-objects-redux
Version: 0.1.2
Summary: Simple Django app for making any object featured.
Home-page: https://github.com/bashu/django-featured-objects-redux
Author: Pedro Buron
Author-email: pedro@witoi.com
Maintainer: Basil Shubin
Maintainer-email: basil.shubin@gmail.com
License: GPLv3 License
Download-URL: https://github.com/bashu/django-featured-objects-redux/zipball/master
Platform: UNKNOWN
Classifier: Development Status :: 4 - Beta
Classifier: Environment :: Web Environment
Classifier: Framework :: Django
Classifier: Intended Audience :: Developers
Classifier: License :: OSI Approved :: GNU General Public License v3 (GPLv3)
Classifier: Operating System :: OS Independent
Classifier: Programming Language :: Python
Classifier: Programming Language :: Python :: 2
Classifier: Programming Language :: Python :: 2.7
Classifier: Programming Language :: Python :: 3
Classifier: Programming Language :: Python :: 3.4
Classifier: Programming Language :: Python :: 3.5
Classifier: Programming Language :: Python :: 3.6
Classifier: Programming Language :: Python :: 3.7
Classifier: Topic :: Internet :: WWW/HTTP
Classifier: Topic :: Internet :: WWW/HTTP :: Dynamic Content
Requires: Django (>=1.4.2)
Requires-Dist: swapper
